kshgym1/__init__.py
kshgym1/envs/__init__.py
kshgym1/envs/kshgym_env.py
kshgym1-0.0.1.dist-info/METADATA
kshgym1-0.0.1.dist-info/WHEEL
kshgym1-0.0.1.dist-info/top_level.txt
kshgym1-0.0.1.dist-info/RECORD
