Metadata-Version: 2.1
Name: kshgym1
Version: 0.0.1
Summary: A OpenAI Gym Env for foo
Home-page: UNKNOWN
License: UNKNOWN
Platform: UNKNOWN
Requires-Dist: gym
